sumoapputils/__init__.py
sumoapputils/metadata.yaml
sumoapputils/appdev/__init__.py
sumoapputils/appdev/appdeployapi.py
sumoapputils/appdev/appinstall.py
sumoapputils/appdev/apptasks.py
sumoapputils/appdev/cicdtasks.py
sumoapputils/appdev/console.py
sumoapputils/appdev/fifoqueue.py
sumoapputils/appdev/generate_test_config.py
sumoapputils/appdev/runapptests.py
sumoapputils/appdev/secret.json.encrypted
sumoapputils/appdev/updatemanifest.py
sumoapputils/appdev/updatesubmodules.py
sumoapputils/appdev/utils.py
sumoapputils/common/__init__.py
sumoapputils/common/appmanifest.py
sumoapputils/common/autocomplete.py
sumoapputils/common/basetestrunner.py
sumoapputils/common/initapp.py
sumoapputils/common/testapp.py
sumoapputils/common/testutils.py
sumoapputils/common/utils.py
sumoapputils/partner/__init__.py
sumoapputils/partner/console.py
sumoapputils/partner/runapptests.py
sumologic_apptestutils-1.0.9.dist-info/LICENSE
sumologic_apptestutils-1.0.9.dist-info/METADATA
sumologic_apptestutils-1.0.9.dist-info/WHEEL
sumologic_apptestutils-1.0.9.dist-info/entry_points.txt
sumologic_apptestutils-1.0.9.dist-info/top_level.txt
sumologic_apptestutils-1.0.9.dist-info/zip-safe
sumologic_apptestutils-1.0.9.dist-info/RECORD
