Metadata-Version: 2.1
Name: sumologic-apptestutils
Version: 1.0.9
Summary: SumoLogic app testing utitities
Home-page: https://github.com/SumoLogic/sumologic-partner-utils
Author: SumoLogic
Author-email: it@sumologic.com, apps-team@sumologic.com
License: PSF
Keywords: sumologic python rest api log management analytics sumoapptestutils test agent
Platform: UNKNOWN
Classifier: Development Status :: 5 - Production/Stable
Classifier: Intended Audience :: Developers
Classifier: Programming Language :: Python :: 3.7
Classifier: Operating System :: OS Independent
Requires-Dist: sumologic-appclient-sdk (>=1.0.14)
Requires-Dist: click (>=7.0)
Requires-Dist: boto3 (>=1.9.66)
Requires-Dist: click-completion (>=0.5.2)
Requires-Dist: pillow (>=7.1.2)
Requires-Dist: sumologic-sdk (>=0.1.10)
Requires-Dist: pyAesCrypt (>=0.4.3)
Requires-Dist: pyyaml (>=5.4.1)
Requires-Dist: beautifulsoup4 (>=4.9.3)
Provides-Extra: dev
Requires-Dist: twine ; extra == 'dev'
Requires-Dist: wheel ; extra == 'dev'
Requires-Dist: setuptools ; extra == 'dev'
Requires-Dist: check-manifest ; extra == 'dev'
